media_watcher_mcp/__init__.py
media_watcher_mcp/client.py
media_watcher_mcp/server.py
barie_media_watcher_mcp-0.1.2.dist-info/METADATA
barie_media_watcher_mcp-0.1.2.dist-info/WHEEL
barie_media_watcher_mcp-0.1.2.dist-info/entry_points.txt
barie_media_watcher_mcp-0.1.2.dist-info/RECORD
