Metadata-Version: 2.4
Name: barie-media-watcher-mcp
Version: 0.1.2
Summary: Media Watcher MCP Server for performing sentiment analysis and media monitoring via the Model Context Protocol
Author-email: Barie <support@barie.ai>
License: MIT
Keywords: mcp,media,model-context-protocol,news,sentiment,watcher,youtube
Classifier: Development Status :: 4 - Beta
Classifier: Intended Audience :: Developers
Classifier: License :: OSI Approved :: MIT License
Classifier: Programming Language :: Python :: 3
Classifier: Programming Language :: Python :: 3.9
Classifier: Programming Language :: Python :: 3.10
Classifier: Programming Language :: Python :: 3.11
Classifier: Programming Language :: Python :: 3.12
Requires-Python: >=3.9
Requires-Dist: httpx>=0.25.0
Requires-Dist: mcp>=0.9.0
Provides-Extra: dev
Requires-Dist: black>=23.0.0; extra == 'dev'
Requires-Dist: pytest>=7.0.0; extra == 'dev'
Requires-Dist: ruff>=0.1.0; extra == 'dev'
